taloncb/__init__.py
taloncb/constants.py
taloncb/html_quotations.py
taloncb/quotations.py
taloncb/utils.py
taloncb/signature/__init__.py
taloncb/signature/bruteforce.py
taloncb/signature/constants.py
taloncb/signature/extraction.py
taloncb/signature/data/__init__.py
taloncb/signature/data/classifier
taloncb/signature/data/classifier_01.npy
taloncb/signature/data/classifier_02.npy
taloncb/signature/data/classifier_03.npy
taloncb/signature/data/classifier_04.npy
taloncb/signature/data/classifier_05.npy
taloncb/signature/data/train.data
taloncb/signature/learning/__init__.py
taloncb/signature/learning/classifier.py
taloncb/signature/learning/dataset.py
taloncb/signature/learning/featurespace.py
taloncb/signature/learning/helpers.py
taloncb-0.1.4.dist-info/LICENSE
taloncb-0.1.4.dist-info/METADATA
taloncb-0.1.4.dist-info/WHEEL
taloncb-0.1.4.dist-info/top_level.txt
taloncb-0.1.4.dist-info/zip-safe
taloncb-0.1.4.dist-info/RECORD
