Metadata-Version: 2.1
Name: taloncb
Version: 0.1.4
Summary: signature extraction
Home-page: UNKNOWN
Author: camillebrl (Camille Barboule)
Author-email: camille.barboule@gmail.com
License: UNKNOWN
Keywords: python,email,signature
Platform: UNKNOWN
Classifier: Development Status :: 1 - Planning
Classifier: Intended Audience :: Developers
Classifier: Programming Language :: Python :: 3
Classifier: Operating System :: Unix
Classifier: Operating System :: MacOS :: MacOS X
Classifier: Operating System :: Microsoft :: Windows
License-File: LICENSE
Requires-Dist: lxml (>=2.3.3)
Requires-Dist: regex (>=1)
Requires-Dist: numpy
Requires-Dist: scipy
Requires-Dist: scikit-learn (==0.24.1)
Requires-Dist: chardet (>=1.0.1)
Requires-Dist: cchardet (>=0.3.5)
Requires-Dist: cssselect
Requires-Dist: six (>=1.10.0)
Requires-Dist: html5lib
Requires-Dist: joblib
